Workbook

Sheet 📊 Dashboard
A1: SOLVAY – ENERGY EFFICIENCY PROJECT DATABASE | PRODUCTION EXCELLENCE TEAM
A2: Interactive Dashboard – Global Portfolio Overview
A4: KEY PERFORMANCE INDICATORS
A5: Total Projects | C5: Sites Covered | E5: Total Investment (k€) | G5: Total Energy Savings (MWh/yr) | I5: Total Cost Savings (k€/yr) | K5: Total CO2 Reduction (ktCO2/yr) | M5: Avg Payback (yrs) | O5: Projects Completed
A6: =COUNTA('📋 Projects'!A2:A500)-COUNTBLANK('📋 Projects'!A2:A500) -> -385 | C6: =COUNTA('🏭 Sites'!A2:A20)-COUNTBLANK('🏭 Sites'!A2:A20) -> 7 | E6: =SUM('📋 Projects'!I2:I500) -> 60730 | G6: =SUM('📋 Projects'!J2:J500) -> 24907 | I6: =SUM('📋 Projects'!K2:K500) -> 6207 | K6: =SUM('📋 Projects'!L2:L500) -> 7.77 | M6: =IFERROR(AVERAGE('📋 Projects'!M2:M500),0) -> 20.842857 | O6: =COUNTIF('📋 Projects'!G2:G500,"Completed") -> 15
A8: PROJECT STATUS BREAKDOWN | J8: PRIORITY BREAKDOWN
A9: Status | B9: Count | C9: Investment (k€) | D9: Energy Savings (MWh) | E9: Cost Savings (k€) | F9: % of Portfolio | J9: Priority | K9: Count | L9: Avg Investment (k€) | M9: Avg Savings (k€/yr)
A10: Completed | B10: =COUNTIF('📋 Projects'!G:G,A10) -> 15 | C10: =SUMIF('📋 Projects'!G:G,A10,'📋 Projects'!I:I) -> 16748 | D10: =SUMIF('📋 Projects'!G:G,A10,'📋 Projects'!J:J) -> 7684 | E10: =SUMIF('📋 Projects'!G:G,A10,'📋 Projects'!K:K) -> 1620 | F10: =IFERROR(B10/SUM($B$10:$B$13),0) -> 0.26785714 | J10: High | K10: =COUNTIF('📋 Projects'!P:P,J10) -> 32 | L10: =IFERROR(AVERAGEIF('📋 Projects'!P:P,J10,'📋 Projects'!I:I),0) -> 1038.25 | M10: =IFERROR(AVERAGEIF('📋 Projects'!P:P,J10,'📋 Projects'!K:K),0) -> 156.4375
A11: In Progress | B11: =COUNTIF('📋 Projects'!G:G,A11) -> 16 | C11: =SUMIF('📋 Projects'!G:G,A11,'📋 Projects'!I:I) -> 18041 | D11: =SUMIF('📋 Projects'!G:G,A11,'📋 Projects'!J:J) -> 7067 | E11: =SUMIF('📋 Projects'!G:G,A11,'📋 Projects'!K:K) -> 1646 | F11: =IFERROR(B11/SUM($B$10:$B$13),0) -> 0.28571429 | J11: Medium | K11: =COUNTIF('📋 Projects'!P:P,J11) -> 13 | L11: =IFERROR(AVERAGEIF('📋 Projects'!P:P,J11,'📋 Projects'!I:I),0) -> 1120.4615 | M11: =IFERROR(AVERAGEIF('📋 Projects'!P:P,J11,'📋 Projects'!K:K),0) -> 72.769231
A12: Planned | B12: =COUNTIF('📋 Projects'!G:G,A12) -> 12 | C12: =SUMIF('📋 Projects'!G:G,A12,'📋 Projects'!I:I) -> 14805 | D12: =SUMIF('📋 Projects'!G:G,A12,'📋 Projects'!J:J) -> 5239 | E12: =SUMIF('📋 Projects'!G:G,A12,'📋 Projects'!K:K) -> 1519 | F12: =IFERROR(B12/SUM($B$10:$B$13),0) -> 0.21428571 | J12: Low | K12: =COUNTIF('📋 Projects'!P:P,J12) -> 11 | L12: =IFERROR(AVERAGEIF('📋 Projects'!P:P,J12,'📋 Projects'!I:I),0) -> 1176.3636 | M12: =IFERROR(AVERAGEIF('📋 Projects'!P:P,J12,'📋 Projects'!K:K),0) -> 23.181818
A13: Under Study | B13: =COUNTIF('📋 Projects'!G:G,A13) -> 13 | C13: =SUMIF('📋 Projects'!G:G,A13,'📋 Projects'!I:I) -> 11136 | D13: =SUMIF('📋 Projects'!G:G,A13,'📋 Projects'!J:J) -> 4917 | E13: =SUMIF('📋 Projects'!G:G,A13,'📋 Projects'!K:K) -> 1422 | F13: =IFERROR(B13/SUM($B$10:$B$13),0) -> 0.23214286
A15: SITE-LEVEL SUMMARY
A16: Site | B16: Country | C16: Business Unit | D16: # Projects | E16: Investment (k€) | F16: Energy Savings (MWh/yr) | G16: Cost Savings (k€/yr) | H16: CO2 Red. (ktCO2/yr) | I16: Avg Payback (yrs) | J16: # Completed | K16: ISO 50001 | L16: EU Dir. Compliance
A17: Dombasle | B17: France | C17: Soda Ash | D17: =COUNTIF('📋 Projects'!B:B,A17) -> 3 | E17: =SUMIF('📋 Projects'!B:B,A17,'📋 Projects'!I:I) -> 2028 | F17: =SUMIF('📋 Projects'!B:B,A17,'📋 Projects'!J:J) -> 1854 | G17: =SUMIF('📋 Projects'!B:B,A17,'📋 Projects'!K:K) -> 87 | H17: =SUMIF('📋 Projects'!B:B,A17,'📋 Projects'!L:L) -> 0.57 | I17: =IFERROR(AVERAGEIF('📋 Projects'!B:B,A17,'📋 Projects'!M:M),0) -> 84.133333 | J17: =COUNTIFS('📋 Projects'!B:B,A17,'📋 Projects'!G:G,"Completed") -> 1 | K17: =IFERROR(INDEX('📋 Regulatory'!E:E,MATCH(A17,'📋 Regulatory'!A:A,0)),"-") -> Planned | L17: =IFERROR(INDEX('📋 Regulatory'!I:I,MATCH(A17,'📋 Regulatory'!A:A,0)),"-") -> Gap Identified
A18: Jemeppe | B18: Belgium | C18: Silica | D18: =COUNTIF('📋 Projects'!B:B,A18) -> 5 | E18: =SUMIF('📋 Projects'!B:B,A18,'📋 Projects'!I:I) -> 7230 | F18: =SUMIF('📋 Projects'!B:B,A18,'📋 Projects'!J:J) -> 2458 | G18: =SUMIF('📋 Projects'!B:B,A18,'📋 Projects'!K:K) -> 627 | H18: =SUMIF('📋 Projects'!B:B,A18,'📋 Projects'!L:L) -> 1 | I18: =IFERROR(AVERAGEIF('📋 Projects'!B:B,A18,'📋 Projects'!M:M),0) -> 12.36 | J18: =COUNTIFS('📋 Projects'!B:B,A18,'📋 Projects'!G:G,"Completed") -> 0 | K18: =IFERROR(INDEX('📋 Regulatory'!E:E,MATCH(A18,'📋 Regulatory'!A:A,0)),"-") -> Certified | L18: =IFERROR(INDEX('📋 Regulatory'!I:I,MATCH(A18,'📋 Regulatory'!A:A,0)),"-") -> Under Review
A19: Rheinberg | B19: Germany | C19: Hydrogen Peroxide | D19: =COUNTIF('📋 Projects'!B:B,A19) -> 5 | E19: =SUMIF('📋 Projects'!B:B,A19,'📋 Projects'!I:I) -> 5008 | F19: =SUMIF('📋 Projects'!B:B,A19,'📋 Projects'!J:J) -> 2343 | G19: =SUMIF('📋 Projects'!B:B,A19,'📋 Projects'!K:K) -> 418 | H19: =SUMIF('📋 Projects'!B:B,A19,'📋 Projects'!L:L) -> 0.63 | I19: =IFERROR(AVERAGEIF('📋 Projects'!B:B,A19,'📋 Projects'!M:M),0) -> 11.66 | J19: =COUNTIFS('📋 Projects'!B:B,A19,'📋 Projects'!G:G,"Completed") -> 1 | K19: =IFERROR(INDEX('📋 Regulatory'!E:E,MATCH(A19,'📋 Regulatory'!A:A,0)),"-") -> In Progress | L19: =IFERROR(INDEX('📋 Regulatory'!I:I,MATCH(A19,'📋 Regulatory'!A:A,0)),"-") -> Compliant
A20: Martorell | B20: Spain | C20: Specialty Polymers | D20: =COUNTIF('📋 Projects'!B:B,A20) -> 3 | E20: =SUMIF('📋 Projects'!B:B,A20,'📋 Projects'!I:I) -> 4126 | F20: =SUMIF('📋 Projects'!B:B,A20,'📋 Projects'!J:J) -> 890 | G20: =SUMIF('📋 Projects'!B:B,A20,'📋 Projects'!K:K) -> 346 | H20: =SUMIF('📋 Projects'!B:B,A20,'📋 Projects'!L:L) -> 0.3 | I20: =IFERROR(AVERAGEIF('📋 Projects'!B:B,A20,'📋 Projects'!M:M),0) -> 14.333333 | J20: =COUNTIFS('📋 Projects'!B:B,A20,'📋 Projects'!G:G,"Completed") -> 0 | K20: =IFERROR(INDEX('📋 Regulatory'!E:E,MATCH(A20,'📋 Regulatory'!A:A,0)),"-") -> Certified | L20: =IFERROR(INDEX('📋 Regulatory'!I:I,MATCH(A20,'📋 Regulatory'!A:A,0)),"-") -> Partial
A21: Warrington | B21: UK | C21: Silica | D21: =COUNTIF('📋 Projects'!B:B,A21) -> 5 | E21: =SUMIF('📋 Projects'!B:B,A21,'📋 Projects'!I:I) -> 4258 | F21: =SUMIF('📋 Projects'!B:B,A21,'📋 Projects'!J:J) -> 2141 | G21: =SUMIF('📋 Projects'!B:B,A21,'📋 Projects'!K:K) -> 587 | H21: =SUMIF('📋 Projects'!B:B,A21,'📋 Projects'!L:L) -> 0.7 | I21: =IFERROR(AVERAGEIF('📋 Projects'!B:B,A21,'📋 Projects'!M:M),0) -> 19.78 | J21: =COUNTIFS('📋 Projects'!B:B,A21,'📋 Projects'!G:G,"Completed") -> 1 | K21: =IFERROR(INDEX('📋 Regulatory'!E:E,MATCH(A21,'📋 Regulatory'!A:A,0)),"-") -> In Progress | L21: =IFERROR(INDEX('📋 Regulatory'!I:I,MATCH(A21,'📋 Regulatory'!A:A,0)),"-") -> Partial
A22: Tavaux | B22: France | C22: Fluorinated Products | D22: =COUNTIF('📋 Projects'!B:B,A22) -> 3 | E22: =SUMIF('📋 Projects'!B:B,A22,'📋 Projects'!I:I) -> 2589 | F22: =SUMIF('📋 Projects'!B:B,A22,'📋 Projects'!J:J) -> 1071 | G22: =SUMIF('📋 Projects'!B:B,A22,'📋 Projects'!K:K) -> 384 | H22: =SUMIF('📋 Projects'!B:B,A22,'📋 Projects'!L:L) -> 0.28 | I22: =IFERROR(AVERAGEIF('📋 Projects'!B:B,A22,'📋 Projects'!M:M),0) -> 24.366667 | J22: =COUNTIFS('📋 Projects'!B:B,A22,'📋 Projects'!G:G,"Completed") -> 1 | K22: =IFERROR(INDEX('📋 Regulatory'!E:E,MATCH(A22,'📋 Regulatory'!A:A,0)),"-") -> Planned | L22: =IFERROR(INDEX('📋 Regulatory'!I:I,MATCH(A22,'📋 Regulatory'!A:A,0)),"-") -> Partial
A23: Bussi | B23: Italy | C23: Fluorinated Products | D23: =COUNTIF('📋 Projects'!B:B,A23) -> 6 | E23: =SUMIF('📋 Projects'!B:B,A23,'📋 Projects'!I:I) -> 3481 | F23: =SUMIF('📋 Projects'!B:B,A23,'📋 Projects'!J:J) -> 2966 | G23: =SUMIF('📋 Projects'!B:B,A23,'📋 Projects'!K:K) -> 595 | H23: =SUMIF('📋 Projects'!B:B,A23,'📋 Projects'!L:L) -> 0.9 | I23: =IFERROR(AVERAGEIF('📋 Projects'!B:B,A23,'📋 Projects'!M:M),0) -> 14.716667 | J23: =COUNTIFS('📋 Projects'!B:B,A23,'📋 Projects'!G:G,"Completed") -> 2 | K23: =IFERROR(INDEX('📋 Regulatory'!E:E,MATCH(A23,'📋 Regulatory'!A:A,0)),"-") -> In Progress | L23: =IFERROR(INDEX('📋 Regulatory'!I:I,MATCH(A23,'📋 Regulatory'!A:A,0)),"-") -> Partial
A24: Rosignano | B24: Italy | C24: Soda Ash | D24: =COUNTIF('📋 Projects'!B:B,A24) -> 5 | E24: =SUMIF('📋 Projects'!B:B,A24,'📋 Projects'!I:I) -> 5116 | F24: =SUMIF('📋 Projects'!B:B,A24,'📋 Projects'!J:J) -> 2493 | G24: =SUMIF('📋 Projects'!B:B,A24,'📋 Projects'!K:K) -> 676 | H24: =SUMIF('📋 Projects'!B:B,A24,'📋 Projects'!L:L) -> 0.65 | I24: =IFERROR(AVERAGEIF('📋 Projects'!B:B,A24,'📋 Projects'!M:M),0) -> 9.96 | J24: =COUNTIFS('📋 Projects'!B:B,A24,'📋 Projects'!G:G,"Completed") -> 4 | K24: =IFERROR(INDEX('📋 Regulatory'!E:E,MATCH(A24,'📋 Regulatory'!A:A,0)),"-") -> Certified | L24: =IFERROR(INDEX('📋 Regulatory'!I:I,MATCH(A24,'📋 Regulatory'!A:A,0)),"-") -> Under Review
A25: Torrelavega | B25: Spain | C25: Soda Ash | D25: =COUNTIF('📋 Projects'!B:B,A25) -> 5 | E25: =SUMIF('📋 Projects'!B:B,A25,'📋 Projects'!I:I) -> 7963 | F25: =SUMIF('📋 Projects'!B:B,A25,'📋 Projects'!J:J) -> 2555 | G25: =SUMIF('📋 Projects'!B:B,A25,'📋 Projects'!K:K) -> 473 | H25: =SUMIF('📋 Projects'!B:B,A25,'📋 Projects'!L:L) -> 0.67 | I25: =IFERROR(AVERAGEIF('📋 Projects'!B:B,A25,'📋 Projects'!M:M),0) -> 23.68 | J25: =COUNTIFS('📋 Projects'!B:B,A25,'📋 Projects'!G:G,"Completed") -> 2 | K25: =IFERROR(INDEX('📋 Regulatory'!E:E,MATCH(A25,'📋 Regulatory'!A:A,0)),"-") -> Planned | L25: =IFERROR(INDEX('📋 Regulatory'!I:I,MATCH(A25,'📋 Regulatory'!A:A,0)),"-") -> Under Review
A26: Lyon | B26: France | C26: Soda Ash | D26: =COUNTIF('📋 Projects'!B:B,A26) -> 4 | E26: =SUMIF('📋 Projects'!B:B,A26,'📋 Projects'!I:I) -> 6479 | F26: =SUMIF('📋 Projects'!B:B,A26,'📋 Projects'!J:J) -> 1057 | G26: =SUMIF('📋 Projects'!B:B,A26,'📋 Projects'!K:K) -> 314 | H26: =SUMIF('📋 Projects'!B:B,A26,'📋 Projects'!L:L) -> 0.32 | I26: =IFERROR(AVERAGEIF('📋 Projects'!B:B,A26,'📋 Projects'!M:M),0) -> 34.725 | J26: =COUNTIFS('📋 Projects'!B:B,A26,'📋 Projects'!G:G,"Completed") -> 2 | K26: =IFERROR(INDEX('📋 Regulatory'!E:E,MATCH(A26,'📋 Regulatory'!A:A,0)),"-") -> Planned | L26: =IFERROR(INDEX('📋 Regulatory'!I:I,MATCH(A26,'📋 Regulatory'!A:A,0)),"-") -> Gap Identified
A27: Brussels | B27: Belgium | C27: Specialty Polymers | D27: =COUNTIF('📋 Projects'!B:B,A27) -> 6 | E27: =SUMIF('📋 Projects'!B:B,A27,'📋 Projects'!I:I) -> 7491 | F27: =SUMIF('📋 Projects'!B:B,A27,'📋 Projects'!J:J) -> 1643 | G27: =SUMIF('📋 Projects'!B:B,A27,'📋 Projects'!K:K) -> 1045 | H27: =SUMIF('📋 Projects'!B:B,A27,'📋 Projects'!L:L) -> 0.53 | I27: =IFERROR(AVERAGEIF('📋 Projects'!B:B,A27,'📋 Projects'!M:M),0) -> 7.0666667 | J27: =COUNTIFS('📋 Projects'!B:B,A27,'📋 Projects'!G:G,"Completed") -> 1 | K27: =IFERROR(INDEX('📋 Regulatory'!E:E,MATCH(A27,'📋 Regulatory'!A:A,0)),"-") -> Planned | L27: =IFERROR(INDEX('📋 Regulatory'!I:I,MATCH(A27,'📋 Regulatory'!A:A,0)),"-") -> Under Review
A28: Stauffer | B28: Germany | C28: Hydrogen Peroxide | D28: =COUNTIF('📋 Projects'!B:B,A28) -> 6 | E28: =SUMIF('📋 Projects'!B:B,A28,'📋 Projects'!I:I) -> 4961 | F28: =SUMIF('📋 Projects'!B:B,A28,'📋 Projects'!J:J) -> 3436 | G28: =SUMIF('📋 Projects'!B:B,A28,'📋 Projects'!K:K) -> 655 | H28: =SUMIF('📋 Projects'!B:B,A28,'📋 Projects'!L:L) -> 1.22 | I28: =IFERROR(AVERAGEIF('📋 Projects'!B:B,A28,'📋 Projects'!M:M),0) -> 23.65 | J28: =COUNTIFS('📋 Projects'!B:B,A28,'📋 Projects'!G:G,"Completed") -> 0 | K28: =IFERROR(INDEX('📋 Regulatory'!E:E,MATCH(A28,'📋 Regulatory'!A:A,0)),"-") -> Planned | L28: =IFERROR(INDEX('📋 Regulatory'!I:I,MATCH(A28,'📋 Regulatory'!A:A,0)),"-") -> Partial

Sheet 📋 Projects
A1: ENERGY EFFICIENCY PROJECTS DATABASE – ALL SITES
A2: ID | B2: Site | C2: Country | D2: Business Unit | E2: Technology | F2: Project Name | G2: Status | H2: Year | I2: Investment (k€) | J2: Annual Energy Savings (MWh) | K2: Annual Cost Savings (k€) | L2: CO2 Reduction (ktCO2/yr) | M2: Payback (yrs) | N2: NPV (k€) | O2: IRR (%) | P2: Priority
A3: EE-001 | B3: Dombasle | C3: France | D3: Soda Ash | E3: Variable Speed Drive | F3: Variable Speed Drive – Dombasle P1 | G3: Completed | H3: 2026 | I3: 476 | J3: 429 | K3: 10 | L3: 0.11 | M3: 47.6 | N3: -426 | O3: 2.1 | P3: Low
A4: EE-002 | B4: Dombasle | C4: France | D4: Soda Ash | E4: Steam Optimization | F4: Steam Optimization – Dombasle P2 | G4: Under Study | H4: 2026 | I4: 1199 | J4: 657 | K4: 6 | L4: 0.29 | M4: 199.8 | N4: -1169 | O4: 0.5 | P4: Low
A5: EE-003 | B5: Dombasle | C5: France | D5: Soda Ash | E5: Insulation Upgrade | F5: Insulation Upgrade – Dombasle P3 | G5: Planned | H5: 2023 | I5: 353 | J5: 768 | K5: 71 | L5: 0.17 | M5: 5 | N5: 2 | O5: 20.1 | P5: Medium
A6: EE-004 | B6: Jemeppe | C6: Belgium | D6: Silica | E6: Insulation Upgrade | F6: Insulation Upgrade – Jemeppe P1 | G6: Planned | H6: 2026 | I6: 1624 | J6: 597 | K6: 110 | L6: 0.29 | M6: 14.8 | N6: -1074 | O6: 6.8 | P6: High
A7: EE-005 | B7: Jemeppe | C7: Belgium | D7: Silica | E7: LED Lighting | F7: LED Lighting – Jemeppe P2 | G7: Planned | H7: 2023 | I7: 1667 | J7: 514 | K7: 173 | L7: 0.19 | M7: 9.6 | N7: -802 | O7: 10.4 | P7: High
A8: EE-006 | B8: Jemeppe | C8: Belgium | D8: Silica | E8: Variable Speed Drive | F8: Variable Speed Drive – Jemeppe P3 | G8: In Progress | H8: 2026 | I8: 1557 | J8: 789 | K8: 172 | L8: 0.36 | M8: 9.1 | N8: -697 | O8: 11 | P8: High
A9: EE-007 | B9: Jemeppe | C9: Belgium | D9: Silica | E9: Compressed Air Efficiency | F9: Compressed Air Efficiency – Jemeppe P4 | G9: Under Study | H9: 2025 | I9: 1290 | J9: 324 | K9: 77 | L9: 0.09 | M9: 16.8 | N9: -905 | O9: 6 | P9: Medium
A10: EE-008 | B10: Jemeppe | C10: Belgium | D10: Silica | E10: LED Lighting | F10: LED Lighting – Jemeppe P5 | G10: In Progress | H10: 2024 | I10: 1092 | J10: 234 | K10: 95 | L10: 0.07 | M10: 11.5 | N10: -617 | O10: 8.7 | P10: Medium
A11: EE-009 | B11: Rheinberg | C11: Germany | D11: Hydrogen Peroxide | E11: Variable Speed Drive | F11: Variable Speed Drive – Rheinberg P1 | G11: In Progress | H11: 2025 | I11: 1653 | J11: 654 | K11: 83 | L11: 0.14 | M11: 19.9 | N11: -1238 | O11: 5 | P11: Medium
A12: EE-010 | B12: Rheinberg | C12: Germany | D12: Hydrogen Peroxide | E12: Steam Optimization | F12: Steam Optimization – Rheinberg P2 | G12: Under Study | H12: 2024 | I12: 821 | J12: 736 | K12: 94 | L12: 0.21 | M12: 8.7 | N12: -351 | O12: 11.4 | P12: Medium
A13: EE-011 | B13: Rheinberg | C13: Germany | D13: Hydrogen Peroxide | E13: Power Factor Correction | F13: Power Factor Correction – Rheinberg P3 | G13: Planned | H13: 2024 | I13: 1507 | J13: 371 | K13: 119 | L13: 0.11 | M13: 12.7 | N13: -912 | O13: 7.9 | P13: High
A14: EE-012 | B14: Rheinberg | C14: Germany | D14: Hydrogen Peroxide | E14: Power Factor Correction | F14: Power Factor Correction – Rheinberg P4 | G14: Under Study | H14: 2026 | I14: 227 | J14: 85 | K14: 26 | L14: 0.03 | M14: 8.7 | N14: -97 | O14: 11.5 | P14: Low
... A58: EE-056 | B58: Stauffer | C58: Germany | D58: Hydrogen Peroxide | E58: Waste Heat Boiler | F58: Waste Heat Boiler – Stauffer P6 | G58: In Progress | H58: 2023 | I58: 1047 | J58: 645 | K58: 192 | L58: 0.27 | M58: 5.5 | N58: -87 | O58: 18.3 | P58: High

Sheet 🏭 Sites
A1: INDUSTRIAL SITES MASTER LIST
A2: Site ID | B2: Site Name | C2: Country | D2: Business Unit | E2: Annual Energy Consumption (MWh) | F2: Baseline Year | G2: Energy Manager | H2: Contact Email | I2: # Active Projects | J2: Total Investment Pipeline (k€) | K2: Total Savings Potential (k€/yr)
A3: S01 | B3: Dombasle | C3: France | D3: Soda Ash | E3: 460000 | F3: 2007 | G3: François Bernard | H3: f.bernard@solvay.com | I3: =COUNTIF('📋 Projects'!B:B,B3) -> 3 | J3: =SUMIF('📋 Projects'!B:B,B3,'📋 Projects'!I:I) -> 2028 | K3: =SUMIF('📋 Projects'!B:B,B3,'📋 Projects'!K:K) -> 87
A4: S02 | B4: Jemeppe | C4: Belgium | D4: Silica | E4: 210000 | F4: 2009 | G4: Pierre Dubois | H4: p.dubois@solvay.com | I4: =COUNTIF('📋 Projects'!B:B,B4) -> 5 | J4: =SUMIF('📋 Projects'!B:B,B4,'📋 Projects'!I:I) -> 7230 | K4: =SUMIF('📋 Projects'!B:B,B4,'📋 Projects'!K:K) -> 627
A5: S03 | B5: Rheinberg | C5: Germany | D5: Hydrogen Peroxide | E5: 410000 | F5: 2015 | G5: Klaus Müller | H5: k.mueller@solvay.com | I5: =COUNTIF('📋 Projects'!B:B,B5) -> 5 | J5: =SUMIF('📋 Projects'!B:B,B5,'📋 Projects'!I:I) -> 5008 | K5: =SUMIF('📋 Projects'!B:B,B5,'📋 Projects'!K:K) -> 418
A6: S04 | B6: Martorell | C6: Spain | D6: Specialty Polymers | E6: 185000 | F6: 2016 | G6: Carlos López | H6: c.lopez@solvay.com | I6: =COUNTIF('📋 Projects'!B:B,B6) -> 3 | J6: =SUMIF('📋 Projects'!B:B,B6,'📋 Projects'!I:I) -> 4126 | K6: =SUMIF('📋 Projects'!B:B,B6,'📋 Projects'!K:K) -> 346
A7: S05 | B7: Warrington | C7: UK | D7: Silica | E7: 270000 | F7: 2013 | G7: Emma Wilson | H7: e.wilson@solvay.com | I7: =COUNTIF('📋 Projects'!B:B,B7) -> 5 | J7: =SUMIF('📋 Projects'!B:B,B7,'📋 Projects'!I:I) -> 4258 | K7: =SUMIF('📋 Projects'!B:B,B7,'📋 Projects'!K:K) -> 587
A8: S06 | B8: Tavaux | C8: France | D8: Fluorinated Products | E8: 340000 | F8: 2014 | G8: Nathalie Martin | H8: n.martin@solvay.com | I8: =COUNTIF('📋 Projects'!B:B,B8) -> 3 | J8: =SUMIF('📋 Projects'!B:B,B8,'📋 Projects'!I:I) -> 2589 | K8: =SUMIF('📋 Projects'!B:B,B8,'📋 Projects'!K:K) -> 384
A9: S07 | B9: Bussi | C9: Italy | D9: Fluorinated Products | E9: 155000 | F9: 2017 | G9: Lucia Romano | H9: l.romano@solvay.com | I9: =COUNTIF('📋 Projects'!B:B,B9) -> 6 | J9: =SUMIF('📋 Projects'!B:B,B9,'📋 Projects'!I:I) -> 3481 | K9: =SUMIF('📋 Projects'!B:B,B9,'📋 Projects'!K:K) -> 595
A10: S08 | B10: Rosignano | C10: Italy | D10: Soda Ash | E10: 380000 | F10: 2012 | G10: Marco Ferretti | H10: m.ferretti@solvay.com | I10: =COUNTIF('📋 Projects'!B:B,B10) -> 5 | J10: =SUMIF('📋 Projects'!B:B,B10,'📋 Projects'!I:I) -> 5116 | K10: =SUMIF('📋 Projects'!B:B,B10,'📋 Projects'!K:K) -> 676
A11: S09 | B11: Torrelavega | C11: Spain | D11: Soda Ash | E11: 290000 | F11: 2011 | G11: Elena García | H11: e.garcia@solvay.com | I11: =COUNTIF('📋 Projects'!B:B,B11) -> 5 | J11: =SUMIF('📋 Projects'!B:B,B11,'📋 Projects'!I:I) -> 7963 | K11: =SUMIF('📋 Projects'!B:B,B11,'📋 Projects'!K:K) -> 473
A12: S10 | B12: Lyon | C12: France | D12: Soda Ash | E12: 500000 | F12: 2010 | G12: Jean-Paul Moreau | H12: jean-paul.moreau@solvay.com | I12: =COUNTIF('📋 Projects'!B:B,B12) -> 4 | J12: =SUMIF('📋 Projects'!B:B,B12,'📋 Projects'!I:I) -> 6479 | K12: =SUMIF('📋 Projects'!B:B,B12,'📋 Projects'!K:K) -> 314
A13: S11 | B13: Brussels | C13: Belgium | D13: Specialty Polymers | E13: 320000 | F13: 2008 | G13: Sarah Vandenberghe | H13: s.vandenberghe@solvay.com | I13: =COUNTIF('📋 Projects'!B:B,B13) -> 6 | J13: =SUMIF('📋 Projects'!B:B,B13,'📋 Projects'!I:I) -> 7491 | K13: =SUMIF('📋 Projects'!B:B,B13,'📋 Projects'!K:K) -> 1045
A14: S12 | B14: Stauffer | C14: Germany | D14: Hydrogen Peroxide | E14: 195000 | F14: 2018 | G14: Hans Fischer | H14: h.fischer@solvay.com | I14: =COUNTIF('📋 Projects'!B:B,B14) -> 6 | J14: =SUMIF('📋 Projects'!B:B,B14,'📋 Projects'!I:I) -> 4961 | K14: =SUMIF('📋 Projects'!B:B,B14,'📋 Projects'!K:K) -> 655

Sheet 📋 Regulatory
A1: EU REGULATORY COMPLIANCE TRACKER – DIRECTIVE (EU) 2023/1791 | ISO 50001 | ISO 14001
A2: Site | B2: Country | C2: Business Unit | D2: ISO 50001 Status | E2: ISO 14001 Status | F2: Last Energy Audit | G2: Next Audit Due | H2: Audit Status | I2: EU Dir. 2023/1791 Compliance | J2: EnMS Implemented | K2: EMS Scope | L2: Responsible | M2: Comments
A3: Dombasle | B3: France | C3: Soda Ash | D3: Planned | E3: Planned | F3: 2024 | G3: 2025 | H3: Scheduled | I3: Gap Identified | J3: Yes | K3: Full Site | L3: Energy Manager | M3: On track
A4: Jemeppe | B4: Belgium | C4: Silica | D4: Certified | E4: Certified | F4: N/A | G4: 2027 | H4: Completed | I4: Under Review | J4: No | K4: Not Defined | L4: Site Director | M4: Audit delayed
A5: Rheinberg | B5: Germany | C5: Hydrogen Peroxide | D5: Not Started | E5: In Progress | F5: N/A | G5: 2025 | H5: Scheduled | I5: Compliant | J5: Yes | K5: Partial | L5: Energy Manager | M5: Audit delayed
A6: Martorell | B6: Spain | C6: Specialty Polymers | D6: Not Started | E6: Certified | F6: 2023 | G6: 2025 | H6: Not Required | I6: Partial | J6: No | K6: Not Defined | L6: Site Director
A7: Warrington | B7: UK | C7: Silica | D7: Planned | E7: In Progress | F7: N/A | G7: 2027 | H7: Not Required | I7: Partial | J7: In Progress | K7: Partial | L7: HSE Manager | M7: Certification renewal due
A8: Tavaux | B8: France | C8: Fluorinated Products | D8: In Progress | E8: Planned | F8: 2024 | G8: 2027 | H8: Not Required | I8: Partial | J8: No | K8: Partial | L8: Energy Manager | M8: Certification renewal due
A9: Bussi | B9: Italy | C9: Fluorinated Products | D9: In Progress | E9: In Progress | F9: 2024 | G9: 2026 | H9: Completed | I9: Partial | J9: Yes | K9: Full Site | L9: HSE Manager | M9: Audit delayed
A10: Rosignano | B10: Italy | C10: Soda Ash | D10: In Progress | E10: Certified | F10: N/A | G10: 2026 | H10: Overdue | I10: Under Review | J10: No | K10: Full Site | L10: Energy Manager | M10: New system deployed
A11: Torrelavega | B11: Spain | C11: Soda Ash | D11: Not Started | E11: Planned | F11: 2022 | G11: 2027 | H11: Not Required | I11: Under Review | J11: Yes | K11: Partial | L11: HSE Manager | M11: New system deployed
A12: Lyon | B12: France | C12: Soda Ash | D12: Not Started | E12: Planned | F12: 2023 | G12: 2026 | H12: Scheduled | I12: Gap Identified | J12: No | K12: Partial | L12: Energy Manager | M12: New system deployed
A13: Brussels | B13: Belgium | C13: Specialty Polymers | D13: Planned | E13: Planned | F13: N/A | G13: 2027 | H13: Scheduled | I13: Under Review | J13: Yes | K13: Not Defined | L13: Site Director | M13: On track
A14: Stauffer | B14: Germany | C14: Hydrogen Peroxide | D14: Not Started | E14: Planned | F14: 2022 | G14: 2025 | H14: Not Required | I14: Partial | J14: No | K14: Full Site | L14: Energy Manager | M14: Certification renewal due

Sheet 🚀 Startup Matchmaking
A1: ENERGY EFFICIENCY STARTUP MATCHMAKING MATRIX
A2: Startup Name | B2: Solution Description | C2: Technology Category | D2: HQ Country | E2: Funding Stage | F2: Applicable Project Types | G2: # Matching Projects (DB) | H2: Potential Sites | I2: Match Score | J2: Recommended Action
A3: VoltAI | B3: AI-based energy monitoring | C3: Digital / IoT | D3: France | E3: Seed | F3: Motor Upgrade, Process Optimization | G3: =COUNTIF('📋 Projects'!E:E,"Motor Upgrade") -> 0 | H3: Jemeppe | I3: 84 | J3: Monitor
A4: ThermoLoop | B4: Industrial heat recovery systems | C4: Heat Recovery | D4: Germany | E4: Series A | F4: Heat Recovery, Waste Heat Boiler | G4: =COUNTIF('📋 Projects'!E:E,"Heat Recovery") -> 4 | H4: Rheinberg | I4: 89 | J4: Monitor
A5: AirWise | B5: Compressed air leak detection | C5: Compressed Air | D5: Belgium | E5: Seed | F5: Compressed Air Efficiency | G5: =COUNTIF('📋 Projects'!E:E,"Compressed Air Efficiency") -> 7 | H5: Martorell | I5: 84 | J5: Monitor
A6: PowerSync | B6: Power factor correction units | C6: Power Quality | D6: Spain | E6: Series B | F6: Power Factor Correction | G6: =COUNTIF('📋 Projects'!E:E,"Power Factor Correction") -> 6 | H6: Martorell | I6: 76 | J6: Pilot Recommended
A7: LumaTech | B7: Smart LED industrial lighting | C7: Lighting | D7: Italy | E7: Series A | F7: LED Lighting | G7: =COUNTIF('📋 Projects'!E:E,"LED Lighting") -> 8 | H7: Rheinberg | I7: 61 | J7: Pilot Recommended
A8: DriveFlow | B8: Variable speed drive retrofits | C8: Drives | D8: Germany | E8: Series B | F8: Variable Speed Drive | G8: =COUNTIF('📋 Projects'!E:E,"Variable Speed Drive") -> 7 | H8: Tavaux | I8: 74 | J8: Pilot Recommended
A9: IsoShield | B9: Advanced insulation materials | C9: Insulation | D9: France | E9: Seed | F9: Insulation Upgrade | G9: =COUNTIF('📋 Projects'!E:E,"Insulation Upgrade") -> 5 | H9: Jemeppe | I9: 62 | J9: Pilot Recommended
A10: SteamIQ | B10: Steam system optimisation platform | C10: Steam | D10: UK | E10: Series A | F10: Steam Optimization | G10: =COUNTIF('📋 Projects'!E:E,"Steam Optimization") -> 7 | H10: Warrington | I10: 72 | J10: Pilot Recommended
A11: MotorEdge | B11: High-efficiency motor solutions | C11: Motors | D11: Belgium | E11: Seed | F11: Electric Motor Upgrade | G11: =COUNTIF('📋 Projects'!E:E,"Electric Motor Upgrade") -> 3 | H11: Jemeppe | I11: 69 | J11: Assess Further
A12: DataEnergy | B12: Energy analytics & reporting | C12: Digital / IoT | D12: France | E12: Series B | F12: Process Optimization, Compressed Air Efficiency | G12: =COUNTIF('📋 Projects'!E:E,"Process Optimization") -> 5 | H12: Warrington | I12: 90 | J12: Pilot Recommended

Sheet 🧮 TechEco Calculator
A1: TECHNO-ECONOMIC EVALUATION TOOL
A2: Enter project inputs (blue cells) → outputs calculated automatically
A4: INPUTS
A5: Project Name | B5: My Energy Project
A6: Site | B6: Lyon
A7: Technology Type | B7: Variable Speed Drive
A8: Investment Cost (k€) | B8: 500 | C8: k€
A9: Annual Energy Savings (MWh/yr) | B9: 300 | C9: MWh/yr
A10: Energy Unit Cost (€/MWh) | B10: 80 | C10: €/MWh
A11: Project Lifetime (yrs) | B11: 10 | C11: yrs
A12: Discount Rate (%) | B12: 8 | C12: %
A13: CO2 Emission Factor (tCO2/MWh) | B13: 0.35 | C13: tCO2/MWh
A17: CALCULATED OUTPUTS
A18: Annual Cost Savings (k€/yr) | B18: =B10*B11/1000 -> 0.8 | C18: k€/yr
A19: Simple Payback Period (yrs) | B19: =IFERROR(B9/B18,0) -> 375 | C19: yrs
A20: Total Lifetime Savings (k€) | B20: =B18*B12 -> 6.4 | C20: k€
A21: Net Present Value (k€) | B21: =IFERROR(B18*((1-(1+B13/100)^(-B12))/(B13/100))-B9,0) -> -293.69964 | C21: k€
A22: Internal Rate of Return (%) | B22: =IFERROR((B18/B9)*100,0) -> 0.26666667 | C22: %
A23: CO2 Reduction (tCO2/yr) | B23: =B10*B14 -> 0 | C23: tCO2/yr
A24: CO2 Reduction over Lifetime (tCO2) | B24: =B10*B14*B12 -> 0 | C24: tCO2
A25: € saved per tCO2 (€/tCO2) | B25: =IFERROR((B18*1000)/( B10*B14),0) -> 0 | C25: €/tCO2

Sheet 📖 Legend & Instructions
A1: USER GUIDE & LEGEND
A3: SHEET DESCRIPTIONS
A4: 📊 Dashboard | B4: Auto-calculated KPI summary. Do not edit formula cells. Refresh by updating Projects sheet.
A5: 📋 Projects | B5: Main database. Add rows below existing data. Blue cells = inputs. Use dropdown for Status & Priority.
A6: 🏭 Sites | B6: Master site list. Energy consumption & baseline year are manual inputs (blue). Totals auto-update.
A7: 📋 Regulatory | B7: EU compliance tracker. Update status fields as audits/certifications progress.
A8: 🚀 Startup Matchmaking | B8: Startup evaluation matrix. Add new startups or update match scores as evaluations complete.
A9: 🧮 TechEco Calculator | B9: Input project parameters in blue cells. All financial outputs recalculate automatically.
A11: COLOR CODING CONVENTION
A12: Blue text | B12: Hardcoded inputs – values you can change
A13: Black text | B13: Formulas / calculated values – do not overwrite
A14: Green text | B14: Cross-sheet links – auto-updated
A15: Green background | B15: Completed / Compliant status
A16: Yellow background | B16: In Progress / Partial status
A17: Red background | B17: Gap Identified / Overdue status
